spire/__init__.py
spire/pdf/FileFormat.py
spire/pdf/Find_TextFindParameter.py
spire/pdf/PdfAlignmentStyle.py
spire/pdf/PdfApplicationData.py
spire/pdf/PdfBorderOverlapStyle.py
spire/pdf/PdfBorders.py
spire/pdf/PdfCollection.py
spire/pdf/PdfCompressionLevel.py
spire/pdf/PdfConformanceLevel.py
spire/pdf/PdfConvertOptions.py
spire/pdf/PdfCrossReferenceType.py
spire/pdf/PdfDockStyle.py
spire/pdf/PdfDocument.py
spire/pdf/PdfDocumentBase.py
spire/pdf/PdfDocumentInformation.py
spire/pdf/PdfDocumentPrivilege.py
spire/pdf/PdfDocumentTemplate.py
spire/pdf/PdfEdges.py
spire/pdf/PdfEncryptionAlgorithm.py
spire/pdf/PdfFileInfo.py
spire/pdf/PdfNewDocument.py
spire/pdf/PdfNewPage.py
spire/pdf/PdfNumberStyle.py
spire/pdf/PdfPaddings.py
spire/pdf/PdfPageBase.py
spire/pdf/PdfPageLabels.py
spire/pdf/PdfPageLayout.py
spire/pdf/PdfPageMode.py
spire/pdf/PdfPageOrientation.py
spire/pdf/PdfPageRotateAngle.py
spire/pdf/PdfPageSettings.py
spire/pdf/PdfPageSize.py
spire/pdf/PdfPageTemplateElement.py
spire/pdf/PdfPageTransition.py
spire/pdf/PdfPageWidget.py
spire/pdf/PdfPasswordSecurityPolicy.py
spire/pdf/PdfPieceInfo.py
spire/pdf/PdfSection.py
spire/pdf/PdfSectionCollection.py
spire/pdf/PdfSectionPageCollection.py
spire/pdf/PdfSectionTemplate.py
spire/pdf/PdfSecurityPolicy.py
spire/pdf/PdfStampCollection.py
spire/pdf/PdfTransitionDimension.py
spire/pdf/PdfTransitionDirection.py
spire/pdf/PdfTransitionMotion.py
spire/pdf/PdfTransitionStyle.py
spire/pdf/PdfVersion.py
spire/pdf/PdfViewerPreferences.py
spire/pdf/PrintScalingMode.py
spire/pdf/TabOrder.py
spire/pdf/__init__.py
spire/pdf/actions/PdfAction.py
spire/pdf/actions/PdfActionCollection.py
spire/pdf/actions/PdfActionDestination.py
spire/pdf/actions/PdfAnnotationActions.py
spire/pdf/actions/PdfDocumentActions.py
spire/pdf/actions/PdfEmbeddedGoToAction.py
spire/pdf/actions/PdfFieldActions.py
spire/pdf/actions/PdfFilePathType.py
spire/pdf/actions/PdfFormAction.py
spire/pdf/actions/PdfGoToAction.py
spire/pdf/actions/PdfGotoNameAction.py
spire_pdf-11.12.1.dist-info/METADATA
spire_pdf-11.12.1.dist-info/WHEEL
spire_pdf-11.12.1.dist-info/top_level.txt
spire_pdf-11.12.1.dist-info/RECORD
